README.rst
setup.py
abci/__init__.py
abci/application.py
abci/encoding.py
abci/server.py
abci/utils.py
examples/__init__.py
examples/counter.py
github/__init__.py
github/com/__init__.py
github/com/gogo/__init__.py
github/com/gogo/protobuf/__init__.py
github/com/gogo/protobuf/gogoproto/__init__.py
github/com/gogo/protobuf/gogoproto/gogo_pb2.py
github/com/tendermint/__init__.py
github/com/tendermint/tendermint/__init__.py
github/com/tendermint/tendermint/abci/__init__.py
github/com/tendermint/tendermint/abci/types/__init__.py
github/com/tendermint/tendermint/abci/types/types_pb2.py
github/com/tendermint/tendermint/crypto/__init__.py
github/com/tendermint/tendermint/crypto/merkle/__init__.py
github/com/tendermint/tendermint/crypto/merkle/merkle_pb2.py
github/com/tendermint/tendermint/libs/__init__.py
github/com/tendermint/tendermint/libs/common/__init__.py
github/com/tendermint/tendermint/libs/common/types_pb2.py
mt_abci.egg-info/PKG-INFO
mt_abci.egg-info/SOURCES.txt
mt_abci.egg-info/dependency_links.txt
mt_abci.egg-info/requires.txt
mt_abci.egg-info/top_level.txt