Metadata-Version: 1.2
Name: mt-abci
Version: 0.6.0
Summary: Python based ABCI Server for Tendermint
Home-page: https://github.com/tavanarad/mt-abci
Author: Morteza Tavanard
License: Apache 2.0
Keywords: blockchain tendermint abci
Platform: UNKNOWN
Classifier: Development Status :: 3 - Alpha
Classifier: Intended Audience :: Developers
Classifier: License :: OSI Approved :: Apache Software License
Classifier: Programming Language :: Python :: 3.6
Requires-Python: >=3.6
